{
  "title": "PRM (Process Reward Model) 过程奖励模型",
  "subtitle": "对思维链中的每一步进行打分，而非仅对最终结果评分",
  "content": [
    {
      "type": "section",
      "title": "📖 核心概念",
      "content": [
        {
          "type": "desc-box",
          "content": [
            "PRM是一种过程奖励模型，不同于传统的只对最终结果评分的奖励模型，PRM会对思维链推理过程中的每一步进行打分。通过评估推理过程的正确性，显著提升模型在复杂逻辑推理任务上的正确率。"
          ]
        }
      ]
    },
    {
      "type": "section",
      "title": "🌟 核心特点",
      "content": [
        {
          "type": "features",
          "items": [
            "过程评估：对推理过程的每一步进行评分，而非仅看最终结果",
            "错误定位：能够识别推理过程中的错误步骤",
            "性能提升：在数学推理、逻辑推理等任务上显著提升正确率",
            "训练信号：为模型提供更细粒度的训练信号",
            "可解释性：通过过程评分提升模型推理的可解释性"
          ]
        }
      ]
    },
    {
      "type": "section",
      "title": "⚙️ 关键技术",
      "content": [
        {
          "type": "tech-box",
          "content": "过程评分、思维链评估、奖励模型训练、推理质量度量"
        }
      ]
    },
    {
      "type": "section",
      "title": "🚀 应用场景",
      "content": [
        {
          "type": "app-box",
          "content": "数学推理、逻辑推理、代码生成、复杂问题求解等需要多步推理的任务"
        }
      ]
    }
  ]
}
