{
  "title": "Ring Attention 环形注意力",
  "subtitle": "通过环形通信实现超长序列并行处理",
  "content": [
    {
      "type": "section",
      "title": "📖 核心概念",
      "content": [
        {
          "type": "desc-box",
          "content": [
            "Ring Attention是一种分布式注意力机制，通过环形通信模式将超长序列分片到多个设备上并行处理。每个设备处理序列的一部分，通过环形通信传递注意力信息，实现了对超长序列的高效并行处理。"
          ]
        }
      ]
    },
    {
      "type": "section",
      "title": "🌟 核心特点",
      "content": [
        {
          "type": "features",
          "items": [
            "环形通信：通过环形拓扑进行设备间通信",
            "并行处理：多个设备并行处理超长序列",
            "显存分散：将显存需求分散到多个设备",
            "扩展性强：可以扩展到更多设备处理更长序列",
            "效率优化：优化的通信模式，减少通信开销"
          ]
        }
      ]
    },
    {
      "type": "section",
      "title": "⚙️ 关键技术",
      "content": [
        {
          "type": "tech-box",
          "content": "环形拓扑、序列分片、设备间通信、注意力计算、并行优化"
        }
      ]
    },
    {
      "type": "section",
      "title": "🚀 应用场景",
      "content": [
        {
          "type": "app-box",
          "content": "超长序列训练、大规模模型训练、多设备协同、长文本处理"
        }
      ]
    }
  ]
}
